imzml2isa_qt/__init__.py
imzml2isa_qt/__main__.py
imzml2isa_qt/contact.py
imzml2isa_qt/hook-openpyxl.py
imzml2isa_qt/main.py
imzml2isa_qt/ols.py
imzml2isa_qt/parserprogress.py
imzml2isa_qt/scrapers.py
imzml2isa_qt/usermeta.py
imzml2isa_qt/ontologies/pro.json
imzml2isa_qt/ontologies/pso.json
imzml2isa_qt/qt/__init__.py
imzml2isa_qt/qt/contact.py
imzml2isa_qt/qt/help.py
imzml2isa_qt/qt/main.py
imzml2isa_qt/qt/ols.py
imzml2isa_qt/qt/progress.py
imzml2isa_qt/qt/resources_rc.py
imzml2isa_qt/qt/usermeta.py
imzml2isa_qt-0.1.6.dist-info/DESCRIPTION.rst
imzml2isa_qt-0.1.6.dist-info/METADATA
imzml2isa_qt-0.1.6.dist-info/RECORD
imzml2isa_qt-0.1.6.dist-info/WHEEL
imzml2isa_qt-0.1.6.dist-info/entry_points.txt
imzml2isa_qt-0.1.6.dist-info/metadata.json
imzml2isa_qt-0.1.6.dist-info/top_level.txt
